{
  "configVersion": 1,
  "timestamp": 1599185403903,
  "index": "/index.html",
  "assetGroups": [
    {
      "name": "app",
      "installMode": "prefetch",
      "updateMode": "prefetch",
      "cacheQueryOptions": {
        "ignoreVary": true
      },
      "urls": [
        "/favicon.ico",
        "/index.html",
        "/main.074f50160062223ed837.js",
        "/manifest.webmanifest",
        "/polyfills.a4021de53358bb0fec14.js",
        "/runtime.e227d1a0e31cbccbf8ec.js",
        "/styles.ec791a35f1a22ee53ea0.css"
      ],
      "patterns": []
    },
    {
      "name": "assets",
      "installMode": "lazy",
      "updateMode": "prefetch",
      "cacheQueryOptions": {
        "ignoreVary": true
      },
      "urls": [
        "/assets/icons/icon-128x128.png",
        "/assets/icons/icon-144x144.png",
        "/assets/icons/icon-152x152.png",
        "/assets/icons/icon-192x192.png",
        "/assets/icons/icon-384x384.png",
        "/assets/icons/icon-512x512.png",
        "/assets/icons/icon-72x72.png",
        "/assets/icons/icon-96x96.png",
        "/assets/img/AI.png",
        "/assets/img/ab.png",
        "/assets/img/abusolab.jpg",
        "/assets/img/baby.jpg",
        "/assets/img/boys.jpg",
        "/assets/img/close.png",
        "/assets/img/cry.jpg",
        "/assets/img/first-section-bg.png",
        "/assets/img/fivth-section-bg.png",
        "/assets/img/footer-bg.png",
        "/assets/img/heading-bg.png",
        "/assets/img/idea.png",
        "/assets/img/loading.gif",
        "/assets/img/local.png",
        "/assets/img/mujer.jpg",
        "/assets/img/mujer1.jpg",
        "/assets/img/mujeres.jpg",
        "/assets/img/next.png",
        "/assets/img/organ.jpg",
        "/assets/img/phone.png",
        "/assets/img/poor.jpg",
        "/assets/img/poor1.jpg",
        "/assets/img/prev.png",
        "/assets/img/prost.jpg",
        "/assets/img/safe.png",
        "/assets/img/third-section-bg.png",
        "/close.0cfd6489536ec0987466.png",
        "/first-section-bg.aa2b991f447760bf298c.png",
        "/fivth-section-bg.9f4a5b759ed3263041a8.png",
        "/fontawesome-webfont.1e59d2330b4c6deb84b3.ttf",
        "/fontawesome-webfont.20fd1704ea223900efa9.woff2",
        "/fontawesome-webfont.8b43027f47b20503057d.eot",
        "/fontawesome-webfont.c1e38fd9e0e74ba58f7a.svg",
        "/fontawesome-webfont.f691f37e57f04c152e23.woff",
        "/footer-bg.f3cc012dd239a3ff8cca.png",
        "/glyphicons-halflings-regular.2810d2a49be3af435f61.eot",
        "/glyphicons-halflings-regular.a2d98995549db87fb48d.svg",
        "/glyphicons-halflings-regular.b7c243015cec15850248.ttf",
        "/glyphicons-halflings-regular.e3cab037268b4e02bef8.woff",
        "/heading-bg.c6b34478a10eff6ed43f.png",
        "/loading.f657825a2eeed04632b0.gif",
        "/next.62074ac70bd3cfc10445.png",
        "/prev.0edc57ccafb3ea818597.png",
        "/third-section-bg.2dfe1f6bc4393704278b.png"
      ],
      "patterns": []
    }
  ],
  "dataGroups": [],
  "hashTable": {
    "/assets/icons/icon-128x128.png": "dae3b6ed49bdaf4327b92531d4b5b4a5d30c7532",
    "/assets/icons/icon-144x144.png": "b0bd89982e08f9bd2b642928f5391915b74799a7",
    "/assets/icons/icon-152x152.png": "7479a9477815dfd9668d60f8b3b2fba709b91310",
    "/assets/icons/icon-192x192.png": "1abd80d431a237a853ce38147d8c63752f10933b",
    "/assets/icons/icon-384x384.png": "329749cd6393768d3131ed6304c136b1ca05f2fd",
    "/assets/icons/icon-512x512.png": "559d9c4318b45a1f2b10596bbb4c960fe521dbcc",
    "/assets/icons/icon-72x72.png": "c457e56089a36952cd67156f9996bc4ce54a5ed9",
    "/assets/icons/icon-96x96.png": "3914125a4b445bf111c5627875fc190f560daa41",
    "/assets/img/AI.png": "286b9408f7de45bb8b06ec8e28764efe375ec3f9",
    "/assets/img/ab.png": "59e85cea8a2ea0f21d6d4f15f3b6c429739f1a10",
    "/assets/img/abusolab.jpg": "8d420bd312781a4541d6df089a002e11af79c0b3",
    "/assets/img/baby.jpg": "bad0b68e7282586c5afa4687759f552de81fc49b",
    "/assets/img/boys.jpg": "d20538c5b207639882f7f7da25e3fee08b00a192",
    "/assets/img/close.png": "3ca48361cfe0e41163023d03c26296f375bb3eac",
    "/assets/img/cry.jpg": "f0058e3332453d791ec21e5a75ff58869cfee8a1",
    "/assets/img/first-section-bg.png": "19e5b835987eef0e6747fc08ee5a8353f0dd498c",
    "/assets/img/fivth-section-bg.png": "3cf3584c099fff655eb70dbcda4f2a0c69c24a81",
    "/assets/img/footer-bg.png": "0572bdd19a94f61ca4fb82f7eda427096c63b41e",
    "/assets/img/heading-bg.png": "13749f8e6137102d33cff329e3e46f5fd4d00bbd",
    "/assets/img/idea.png": "2c10d4e9de95f7aa3347ba30166685ecc08f2239",
    "/assets/img/loading.gif": "cf720b50cf8dde0e1a84ce1c6a77788bfc5882d5",
    "/assets/img/local.png": "ae61ccd7997cde5f3d148afeb76c1bdba635831b",
    "/assets/img/mujer.jpg": "b649b30662fbc155d6213e5316ecf296b8bc7d1b",
    "/assets/img/mujer1.jpg": "9847948f7f2e050bec4587970e5e3c759b438092",
    "/assets/img/mujeres.jpg": "e1b554ee96b218f905da71e3336d26956d4f1df9",
    "/assets/img/next.png": "777e92c050f600b4519299c3d786b8f2f459fea4",
    "/assets/img/organ.jpg": "dd7afe49ace232100ebfe7fd5331992b60776a30",
    "/assets/img/phone.png": "829b2fcb453d69d7aae5247dab205e97ca632db0",
    "/assets/img/poor.jpg": "436597496f465252e3b7c924a5378226c77fbb9b",
    "/assets/img/poor1.jpg": "092a61d98ca5d131981be68c420968ddb4dc984d",
    "/assets/img/prev.png": "6640a3432f7ba7aea6129cdf7a5d3eabd47c295c",
    "/assets/img/prost.jpg": "63c5519ac4b2f482afa16e86e665b95d0286bf99",
    "/assets/img/safe.png": "07b82ff4bba6848447f3ac749eb8d2e79a9c4a6a",
    "/assets/img/third-section-bg.png": "4f8e83422d2a991dcb0323cb83d9573d5ae1a877",
    "/close.0cfd6489536ec0987466.png": "3ca48361cfe0e41163023d03c26296f375bb3eac",
    "/favicon.ico": "22f6a4a3bcaafafb0254e0f2fa4ceb89e505e8b2",
    "/first-section-bg.aa2b991f447760bf298c.png": "19e5b835987eef0e6747fc08ee5a8353f0dd498c",
    "/fivth-section-bg.9f4a5b759ed3263041a8.png": "3cf3584c099fff655eb70dbcda4f2a0c69c24a81",
    "/fontawesome-webfont.1e59d2330b4c6deb84b3.ttf": "13b1eab65a983c7a73bc7997c479d66943f7c6cb",
    "/fontawesome-webfont.20fd1704ea223900efa9.woff2": "d6f48cba7d076fb6f2fd6ba993a75b9dc1ecbf0c",
    "/fontawesome-webfont.8b43027f47b20503057d.eot": "d980c2ce873dc43af460d4d572d441304499f400",
    "/fontawesome-webfont.c1e38fd9e0e74ba58f7a.svg": "98a8aa5cf7d62c2eff5f07ede8d844b874ef06ed",
    "/fontawesome-webfont.f691f37e57f04c152e23.woff": "28b782240b3e76db824e12c02754a9731a167527",
    "/footer-bg.f3cc012dd239a3ff8cca.png": "0572bdd19a94f61ca4fb82f7eda427096c63b41e",
    "/glyphicons-halflings-regular.2810d2a49be3af435f61.eot": "f3a9a3b609133c3d21d6b42abbf7f43bd111df72",
    "/glyphicons-halflings-regular.a2d98995549db87fb48d.svg": "66b1fc67e37d01ee45ca75c4eefb144d2dbe98fa",
    "/glyphicons-halflings-regular.b7c243015cec15850248.ttf": "aafafdc09404c4aa4447d7e898a2183def9cc1b1",
    "/glyphicons-halflings-regular.e3cab037268b4e02bef8.woff": "22037a3455914e5662fa51a596677bdb329e2c5c",
    "/heading-bg.c6b34478a10eff6ed43f.png": "13749f8e6137102d33cff329e3e46f5fd4d00bbd",
    "/index.html": "2462170c12a90ab82863662a1ad7af4e93031570",
    "/loading.f657825a2eeed04632b0.gif": "cf720b50cf8dde0e1a84ce1c6a77788bfc5882d5",
    "/main.074f50160062223ed837.js": "b6ee97acde6811cf19d6e1b0bc980c768f061cd1",
    "/manifest.webmanifest": "83bb4ce14eba564588c49a795ba1afa33db99443",
    "/next.62074ac70bd3cfc10445.png": "777e92c050f600b4519299c3d786b8f2f459fea4",
    "/polyfills.a4021de53358bb0fec14.js": "b47435a9ef2a4829f2f9dfd35599bde3614981b1",
    "/prev.0edc57ccafb3ea818597.png": "6640a3432f7ba7aea6129cdf7a5d3eabd47c295c",
    "/runtime.e227d1a0e31cbccbf8ec.js": "a9aafcf49f49145093fc831efd9b8e2f6c71bb9c",
    "/styles.ec791a35f1a22ee53ea0.css": "af8726c63dc57c877d35982388eb8ffcc8cc600b",
    "/third-section-bg.2dfe1f6bc4393704278b.png": "4f8e83422d2a991dcb0323cb83d9573d5ae1a877"
  },
  "navigationUrls": [
    {
      "positive": true,
      "regex": "^\\/.*$"
    },
    {
      "positive": false,
      "regex": "^\\/(?:.+\\/)?[^/]*\\.[^/]*$"
    },
    {
      "positive": false,
      "regex": "^\\/(?:.+\\/)?[^/]*__[^/]*$"
    },
    {
      "positive": false,
      "regex": "^\\/(?:.+\\/)?[^/]*__[^/]*\\/.*$"
    }
  ]
}